{"description":"Affiliate Marketing Network","entity_type":"api","entity_url":"https://wiki.awin.com/index.php/API","label":"Awin","name":"awin","singer_name":"tap-awin","type":"tap","variants":[{"default":true,"maintenance_status":"active","meltano_sdk":true,"name":"gthesheep","pip_url":"git+https://github.com/gthesheep/tap-awin.git","repo":"https://github.com/gthesheep/tap-awin","settings_group_validation":[["api_token","lookback_days","start_date"]],"settings":[{"name":"api_token","label":"API token","kind":"password","description":"API Token for the Awin API"},{"name":"lookback_days","label":"Lookback days","description":"Number of days to lookback for transaction updates"},{"name":"start_date","label":"Start date","description":"Start date as of when to collect transactions from"}],"capabilities":["catalog","discover","state","about","stream-maps"],"maintainer":{"label":"Gary James","url":"https://github.com/gthesheep","plugins":[{"url":"/taps/awin--gthesheep","logo_url":"/assets/logos/taps/awin.png","label":"Awin"},{"url":"/taps/bazaarvoice--gthesheep","logo_url":"/assets/logos/taps/bazaarvoice.png","label":"Bazaarvoice"},{"url":"/taps/monday--gthesheep","logo_url":"/assets/logos/taps/monday.png","label":"Monday.com"},{"url":"/taps/pinterest-ads--gthesheep","logo_url":"/assets/logos/taps/pinterest-ads.png","label":"Pinterest Ads"},{"url":"/taps/tableau--gthesheep","logo_url":"/assets/logos/taps/tableau.png","label":"Tableau"},{"url":"/taps/talkable--gthesheep","logo_url":"/assets/logos/taps/talkable.png","label":"Talkable"}],"page_url":"/singer/maintainers/gthesheep"},"metrics":null,"url":"/taps/awin--gthesheep"},{"default":false,"maintenance_status":"unknown","name":"horze-international","pip_url":"git+https://github.com/Horze-International/tap-awin-advertiser.git","repo":"https://github.com/Horze-International/tap-awin-advertiser","settings":[],"capabilities":["catalog","discover"],"maintainer":{"label":"Horze International","url":"https://github.com/horze-international","plugins":[{"url":"/taps/awin--horze-international","logo_url":"/assets/logos/taps/awin.png","label":"Awin"},{"url":"/taps/daisycon--horze-international","logo_url":"/assets/logos/taps/daisycon.png","label":"Daisycon"},{"url":"/taps/idealo-click-report--horze-international","logo_url":"/assets/logos/taps/idealo-click-report.png","label":"Idealo"},{"url":"/taps/surveymonkey--horze-international","logo_url":"/assets/logos/taps/surveymonkey.png","label":"SurveyMonkey"}],"page_url":"/singer/maintainers/horze-international"},"metrics":{"CREATED_AT_TIMESTAMP":"2020-07-28 08:33:19 +0000","NUM_OPEN_ISSUES":0,"NUM_FORKS":0,"LAST_PUSH_TIMESTAMP":"2020-12-16 11:39:04 +0000","LAST_UPDATED_TIMESTAMP":"2021-05-24 09:03:49 +0000","NUM_STARGAZERS":0,"MELTANO_PROJECT_ID_COUNT_3M":0,"NUM_WATCHERS":0,"MELTANO_EXEC_COUNT_3M":0},"url":"/taps/awin--horze-international"},{"default":false,"maintenance_status":"unknown","name":"ideavateltd","pip_url":"git+https://github.com/ideavateltd/tap-awin.git","repo":"https://github.com/ideavateltd/tap-awin","settings":[],"capabilities":["catalog","discover"],"maintainer":{"label":"Ideavate Limited","url":"https://ideavate.co.uk/","plugins":[{"url":"/taps/awin--ideavateltd","logo_url":"/assets/logos/taps/awin.png","label":"Awin"},{"url":"/taps/reviewscouk--ideavateltd","logo_url":"/assets/logos/taps/reviewscouk.png","label":"Reviews.io"}],"page_url":"/singer/maintainers/ideavateltd"},"metrics":{"CREATED_AT_TIMESTAMP":"2017-04-19 08:54:10 +0000","NUM_OPEN_ISSUES":1,"NUM_FORKS":0,"LAST_PUSH_TIMESTAMP":"2021-02-20 10:03:37 +0000","LAST_UPDATED_TIMESTAMP":"2021-02-20 10:03:39 +0000","NUM_STARGAZERS":2,"MELTANO_PROJECT_ID_COUNT_3M":1,"NUM_WATCHERS":2,"MELTANO_EXEC_COUNT_3M":1382},"url":"/taps/awin--ideavateltd"}],"logo_url":"/assets/logos/taps/awin.png","url":"/taps/awin"}